Workbook

Sheet Synthèse
B1: ScentSenegal — Synthèse (tableau de bord)
B2: Tous les chiffres se recalculent quand tu changes une hypothèse.
B3: INDICATEURS CLÉS
B4: Trésorerie minimale sur 24 mois | C4: =MIN('Projection 24 mois'!B20:Y20) | D4: ⚠️ Si NÉGATIF : tu manques de cash → ralentis l'acquisition ou augmente l'apport
B5: Trésorerie fin de mois 24 | C5: ='Projection 24 mois'!Y20 | D5: Cash disponible à la fin
B6: Clients actifs fin mois 24 | C6: ='Projection 24 mois'!Y21 | D6: Sur 35+ hôtels ciblés
B7: Revenu mensuel au mois 24 | C7: ='Projection 24 mois'!Y12 | D7: Chiffre d'affaires récurrent
B8: Revenu annualisé (mois 24 ×12) | C8: ='Projection 24 mois'!Y12*12
B9: Marge brute mensuelle au mois 24 | C9: ='Projection 24 mois'!Y16 | D9: Profit récurrent hors apport/CapEx
B10: Total apport personnel injecté (24 mois) | C10: =SUM('Projection 24 mois'!B18:Y18) | D10: Ce que ton salaire aura mis dans le business
B11: Premier mois où la marge couvre les coûts (marge brute > 0) | C11: =IFERROR(MATCH(TRUE,INDEX('Projection 24 mois'!B16:Y16>0,0),0),"n/a") | D11: Mois où le business gagne plus qu'il ne dépense en opérationnel
B13: COMMENT UTILISER CE FICHIER
B14: 1. Onglet 'Hypothèses' : ajuste toutes les cases JAUNES (prix, coûts, taux de change, douane...).
B15: 2. Onglet 'Économie unitaire' : vérifie la marge et le 'retour sur matériel' de chaque palier.
B16: 3. Onglet 'Projection 24 mois' : saisis le nb de NOUVEAUX clients/mois (lignes jaunes).
B17: 4. Reviens ici : si la 'trésorerie minimale' est négative, ton rythme d'acquisition n'est pas finançable.
B18: Code couleur : JAUNE = à saisir · BLEU = calculé · VERT = résultat.
B19: ⚠️ Les coûts terrain (visite, logistique, douane) sont des ESTIMATIONS : remplace-les par tes vrais devis.

Sheet Hypothèses
B1: ScentSenegal — Modèle financier
B2: HYPOTHÈSES (jaune = à ajuster librement)
B4: Taux de change
B5: CFA par 1 CAD | C5: 610 | D5: 1000 $ ≈ 610 000 CFA (ajuste au taux réel)
B6: Prix des abonnements (CFA / mois)
B7: Découverte | C7: 80000 | D7: Hôtels 3★ / boutique
B8: Confort | C8: 150000 | D8: Hôtels 4★ (le plus choisi)
B9: Prestige | C9: 300000 | D9: Hôtels 5★ / palaces
B10: Huiles essentielles
B11: Coût d'un flacon 500 ml (achat) | C11: 11000 | D11: 55 000 CFA / 5 flacons
B12: Flacons / mois — Découverte | C12: 1 | D12: 1 espace
B13: Flacons / mois — Confort | C13: 2 | D13: 2 espaces
B14: Flacons / mois — Prestige | C14: 5 | D14: 4 à 6 flacons
B15: Service terrain (Dakar)
B16: Coût d'une visite (transport+temps opérateur) | C16: 5000 | D16: À CALER avec ton contact local
B17: Visites / mois — Découverte | C17: 1
B18: Visites / mois — Confort | C18: 2
B19: Visites / mois — Prestige | C19: 4 | D19: + technicien dédié
B20: Logistique d'import (huiles)
B21: Logistique amortie / client / mois | C21: 8000 | D21: DHL groupé + douane sur les huiles, réparti
B22: Matériel & CapEx (avant douane)
B23: Diffuseur SS100 (compact) | C23: 26300 | D23: 79 000 CFA / 3
B24: Diffuseur SS200 (grand format) | C24: 67000
B25: Taux de douane / import sur le matériel | C25: 0.2 | D25: Estimation — À VÉRIFIER
B26: Trésorerie & financement
B27: Capital business d'ouverture | C27: 610000 | D27: ≈ 1000 $ au lancement (mois 4 du plan)
B28: Apport personnel / mois | C28: 305000 | D28: ≈ 500 $/mois (règle des 50%)
B29: Dernier mois d'apport personnel | C29: 9 | D29: Au-delà : business autofinancé
B30: Essai gratuit
B31: Décalage de revenu | C31: 1 | D31: Mois d'essai gratuit : le client paie le mois SUIVANT son installation
B33: CapEx matériel par client (calculé, avec douane)
B34: Découverte (1× SS100) | C34: =(Hypothèses!$C$23)*(1+Hypothèses!$C$25)
B35: Confort (2× SS100) | C35: =(2*Hypothèses!$C$23)*(1+Hypothèses!$C$25)
B36: Prestige (1× SS200 + 2× SS100) | C36: =(Hypothèses!$C$24+2*Hypothèses!$C$23)*(1+Hypothèses!$C$25)

Sheet Économie unitaire
B1: ÉCONOMIE UNITAIRE — marge par client et par palier
B3: Par client / mois | C3: Découverte | D3: Confort | E3: Prestige
B4: Revenu mensuel | C4: =Hypothèses!$C$7 | D4: =Hypothèses!$C$8 | E4: =Hypothèses!$C$9
B5: − Coût huiles | C5: =-Hypothèses!$C$12*Hypothèses!$C$11 | D5: =-Hypothèses!$C$13*Hypothèses!$C$11 | E5: =-Hypothèses!$C$14*Hypothèses!$C$11
B6: − Coût visites | C6: =-Hypothèses!$C$17*Hypothèses!$C$16 | D6: =-Hypothèses!$C$18*Hypothèses!$C$16 | E6: =-Hypothèses!$C$19*Hypothèses!$C$16
B7: − Logistique | C7: =-Hypothèses!$C$21 | D7: =-Hypothèses!$C$21 | E7: =-Hypothèses!$C$21
B8: Coût variable total | C8: =SUM(C5:C7) | D8: =SUM(D5:D7) | E8: =SUM(E5:E7)
B9: Marge brute mensuelle | C9: =C4+C8 | D9: =D4+D8 | E9: =E4+E8
B10: Marge brute % | C10: =C9/C4 | D10: =D9/D4 | E10: =E9/E4
B12: CapEx matériel initial (1×) | C12: =Hypothèses!$C$34 | D12: =Hypothèses!$C$35 | E12: =Hypothèses!$C$36
B13: Retour sur matériel (mois) | C13: =C12/C9 | D13: =D12/D9 | E13: =E12/E9
B14: Durée d'engagement (mois) | C14: 12 | D14: 12 | E14: 24
B15: Profit net sur l'engagement | C15: =C9*C14-C12 | D15: =D9*D14-D12 | E15: =E9*E14-E12
B17: Lecture : la marge brute est le profit récurrent par client. Le 'retour sur matériel' = nb de mois pour rembourser le diffuseur.

Sheet Projection 24 mois
A1: PROJECTION DE TRÉSORERIE — 24 MOIS (jaune = nb de nouveaux clients à saisir)
A2: Mois | B2: 1 | C2: 2 | D2: 3 | E2: 4 | F2: 5 | G2: 6 | H2: 7 | I2: 8 | J2: 9 | K2: 10 | L2: 11 | M2: 12 | N2: 13 | O2: 14 | P2: 15 | Q2: 16 | R2: 17 | S2: 18 | T2: 19 | U2: 20 | V2: 21 | W2: 22 | X2: 23 | Y2: 24
A3: Nouveaux — Découverte | B3: 0 | C3: 1 | D3: 1 | E3: 1 | F3: 1 | G3: 1 | H3: 1 | I3: 1 | J3: 1 | K3: 1 | L3: 1 | M3: 1 | N3: 1 | O3: 1 | P3: 1 | Q3: 1 | R3: 1 | S3: 1 | T3: 1 | U3: 1 | V3: 1 | W3: 1 | X3: 1 | Y3: 1
A4: Nouveaux — Confort | B4: 0 | C4: 0 | D4: 0 | E4: 1 | F4: 0 | G4: 1 | H4: 0 | I4: 1 | J4: 0 | K4: 1 | L4: 0 | M4: 1 | N4: 0 | O4: 1 | P4: 0 | Q4: 1 | R4: 0 | S4: 1 | T4: 0 | U4: 1 | V4: 0 | W4: 1 | X4: 0 | Y4: 1
A5: Nouveaux — Prestige | B5: 0 | C5: 0 | D5: 0 | E5: 0 | F5: 0 | G5: 0 | H5: 1 | I5: 0 | J5: 0 | K5: 0 | L5: 0 | M5: 1 | N5: 0 | O5: 0 | P5: 0 | Q5: 0 | R5: 1 | S5: 0 | T5: 0 | U5: 0 | V5: 0 | W5: 1 | X5: 0 | Y5: 0
A6: Déployés — Découverte | B6: =SUM($B3:B3) | C6: =SUM($B3:C3) | D6: =SUM($B3:D3) | E6: =SUM($B3:E3) | F6: =SUM($B3:F3) | G6: =SUM($B3:G3) | H6: =SUM($B3:H3) | I6: =SUM($B3:I3) | ... Y6: =SUM($B3:Y3)
A7: Déployés — Confort | B7: =SUM($B4:B4) | C7: =SUM($B4:C4) | D7: =SUM($B4:D4) | E7: =SUM($B4:E4) | F7: =SUM($B4:F4) | G7: =SUM($B4:G4) | H7: =SUM($B4:H4) | I7: =SUM($B4:I4) | ... Y7: =SUM($B4:Y4)
A8: Déployés — Prestige | B8: =SUM($B5:B5) | C8: =SUM($B5:C5) | D8: =SUM($B5:D5) | E8: =SUM($B5:E5) | F8: =SUM($B5:F5) | G8: =SUM($B5:G5) | H8: =SUM($B5:H5) | I8: =SUM($B5:I5) | ... Y8: =SUM($B5:Y5)
A9: Payants — Découverte | B9: 0 | C9: =SUM($B3:B3) | D9: =SUM($B3:C3) | E9: =SUM($B3:D3) | F9: =SUM($B3:E3) | G9: =SUM($B3:F3) | H9: =SUM($B3:G3) | I9: =SUM($B3:H3) | J9: =SUM($B3:I3) | ... Y9: =SUM($B3:X3)
A10: Payants — Confort | B10: 0 | C10: =SUM($B4:B4) | D10: =SUM($B4:C4) | E10: =SUM($B4:D4) | F10: =SUM($B4:E4) | G10: =SUM($B4:F4) | H10: =SUM($B4:G4) | I10: =SUM($B4:H4) | J10: =SUM($B4:I4) | ... Y10: =SUM($B4:X4)
A11: Payants — Prestige | B11: 0 | C11: =SUM($B5:B5) | D11: =SUM($B5:C5) | E11: =SUM($B5:D5) | F11: =SUM($B5:E5) | G11: =SUM($B5:F5) | H11: =SUM($B5:G5) | I11: =SUM($B5:H5) | J11: =SUM($B5:I5) | ... Y11: =SUM($B5:X5)
A12: REVENU mensuel | B12: =B9*Hypothèses!$C$7+B10*Hypothèses!$C$8+B11*Hypothèses!$C$9 | C12: =C9*Hypothèses!$C$7+C10*Hypothèses!$C$8+C11*Hypothèses!$C$9 | D12: =D9*Hypothèses!$C$7+D10*Hypothèses!$C$8+D11*Hypothèses!$C$9 | E12: =E9*Hypothèses!$C$7+E10*Hypothèses!$C$8+E11*Hypothèses!$C$9 | F12: =F9*Hypothèses!$C$7+F10*Hypothèses!$C$8+F11*Hypothèses!$C$9 | G12: =G9*Hypothèses!$C$7+G10*Hypothèses!$C$8+G11*Hypothèses!$C$9 | H12: =H9*Hypothèses!$C$7+H10*Hypothèses!$C$8+H11*Hypothèses!$C$9 | I12: =I9*Hypothèses!$C$7+I10*Hypothèses!$C$8+I11*Hypothèses!$C$9 | ... Y12: =Y9*Hypothèses!$C$7+Y10*Hypothèses!$C$8+Y11*Hypothèses!$C$9
A13: − Huiles | B13: =-(B6*Hypothèses!$C$12+B7*Hypothèses!$C$13+B8*Hypothèses!$C$14)*Hypothèses!$C$11 | C13: =-(C6*Hypothèses!$C$12+C7*Hypothèses!$C$13+C8*Hypothèses!$C$14)*Hypothèses!$C$11 | D13: =-(D6*Hypothèses!$C$12+D7*Hypothèses!$C$13+D8*Hypothèses!$C$14)*Hypothèses!$C$11 | E13: =-(E6*Hypothèses!$C$12+E7*Hypothèses!$C$13+E8*Hypothèses!$C$14)*Hypothèses!$C$11 | F13: =-(F6*Hypothèses!$C$12+F7*Hypothèses!$C$13+F8*Hypothèses!$C$14)*Hypothèses!$C$11 | G13: =-(G6*Hypothèses!$C$12+G7*Hypothèses!$C$13+G8*Hypothèses!$C$14)*Hypothèses!$C$11 | H13: =-(H6*Hypothèses!$C$12+H7*Hypothèses!$C$13+H8*Hypothèses!$C$14)*Hypothèses!$C$11 | I13: =-(I6*Hypothèses!$C$12+I7*Hypothèses!$C$13+I8*Hypothèses!$C$14)*Hypothèses!$C$11 | ... Y13: =-(Y6*Hypothèses!$C$12+Y7*Hypothèses!$C$13+Y8*Hypothèses!$C$14)*Hypothèses!$C$11
A14: − Visites | B14: =-(B6*Hypothèses!$C$17+B7*Hypothèses!$C$18+B8*Hypothèses!$C$19)*Hypothèses!$C$16 | C14: =-(C6*Hypothèses!$C$17+C7*Hypothèses!$C$18+C8*Hypothèses!$C$19)*Hypothèses!$C$16 | D14: =-(D6*Hypothèses!$C$17+D7*Hypothèses!$C$18+D8*Hypothèses!$C$19)*Hypothèses!$C$16 | E14: =-(E6*Hypothèses!$C$17+E7*Hypothèses!$C$18+E8*Hypothèses!$C$19)*Hypothèses!$C$16 | F14: =-(F6*Hypothèses!$C$17+F7*Hypothèses!$C$18+F8*Hypothèses!$C$19)*Hypothèses!$C$16 | G14: =-(G6*Hypothèses!$C$17+G7*Hypothèses!$C$18+G8*Hypothèses!$C$19)*Hypothèses!$C$16 | H14: =-(H6*Hypothèses!$C$17+H7*Hypothèses!$C$18+H8*Hypothèses!$C$19)*Hypothèses!$C$16 | I14: =-(I6*Hypothèses!$C$17+I7*Hypothèses!$C$18+I8*Hypothèses!$C$19)*Hypothèses!$C$16 | ... Y14: =-(Y6*Hypothèses!$C$17+Y7*Hypothèses!$C$18+Y8*Hypothèses!$C$19)*Hypothèses!$C$16
A15: − Logistique | B15: =-(B6+B7+B8)*Hypothèses!$C$21 | C15: =-(C6+C7+C8)*Hypothèses!$C$21 | D15: =-(D6+D7+D8)*Hypothèses!$C$21 | E15: =-(E6+E7+E8)*Hypothèses!$C$21 | F15: =-(F6+F7+F8)*Hypothèses!$C$21 | G15: =-(G6+G7+G8)*Hypothèses!$C$21 | H15: =-(H6+H7+H8)*Hypothèses!$C$21 | I15: =-(I6+I7+I8)*Hypothèses!$C$21 | ... Y15: =-(Y6+Y7+Y8)*Hypothèses!$C$21
A16: =Marge brute | B16: =B12+B13+B14+B15 | C16: =C12+C13+C14+C15 | D16: =D12+D13+D14+D15 | E16: =E12+E13+E14+E15 | F16: =F12+F13+F14+F15 | G16: =G12+G13+G14+G15 | H16: =H12+H13+H14+H15 | I16: =I12+I13+I14+I15 | ... Y16: =Y12+Y13+Y14+Y15
A17: − CapEx (nouveaux clients) | B17: =-(B3*Hypothèses!$C$34+B4*Hypothèses!$C$35+B5*Hypothèses!$C$36) | C17: =-(C3*Hypothèses!$C$34+C4*Hypothèses!$C$35+C5*Hypothèses!$C$36) | D17: =-(D3*Hypothèses!$C$34+D4*Hypothèses!$C$35+D5*Hypothèses!$C$36) | E17: =-(E3*Hypothèses!$C$34+E4*Hypothèses!$C$35+E5*Hypothèses!$C$36) | F17: =-(F3*Hypothèses!$C$34+F4*Hypothèses!$C$35+F5*Hypothèses!$C$36) | G17: =-(G3*Hypothèses!$C$34+G4*Hypothèses!$C$35+G5*Hypothèses!$C$36) | H17: =-(H3*Hypothèses!$C$34+H4*Hypothèses!$C$35+H5*Hypothèses!$C$36) | I17: =-(I3*Hypothèses!$C$34+I4*Hypothèses!$C$35+I5*Hypothèses!$C$36) | ... Y17: =-(Y3*Hypothèses!$C$34+Y4*Hypothèses!$C$35+Y5*Hypothèses!$C$36)
A18: + Apport personnel | B18: =IF(B2<=Hypothèses!$C$29,Hypothèses!$C$28,0) | C18: =IF(C2<=Hypothèses!$C$29,Hypothèses!$C$28,0) | D18: =IF(D2<=Hypothèses!$C$29,Hypothèses!$C$28,0) | E18: =IF(E2<=Hypothèses!$C$29,Hypothèses!$C$28,0) | F18: =IF(F2<=Hypothèses!$C$29,Hypothèses!$C$28,0) | G18: =IF(G2<=Hypothèses!$C$29,Hypothèses!$C$28,0) | H18: =IF(H2<=Hypothèses!$C$29,Hypothèses!$C$28,0) | I18: =IF(I2<=Hypothèses!$C$29,Hypothèses!$C$28,0) | ... Y18: =IF(Y2<=Hypothèses!$C$29,Hypothèses!$C$28,0)
A19: =Cash-flow net du mois | B19: =B16+B17+B18 | C19: =C16+C17+C18 | D19: =D16+D17+D18 | E19: =E16+E17+E18 | F19: =F16+F17+F18 | G19: =G16+G17+G18 | H19: =H16+H17+H18 | I19: =I16+I17+I18 | ... Y19: =Y16+Y17+Y18
A20: TRÉSORERIE cumulée | B20: =Hypothèses!$C$27+B19 | C20: =B20+C19 | D20: =C20+D19 | E20: =D20+E19 | F20: =E20+F19 | G20: =F20+G19 | H20: =G20+H19 | I20: =H20+I19 | J20: =I20+J19 | ... Y20: =X20+Y19
A21: Clients actifs (total) | B21: =B6+B7+B8 | C21: =C6+C7+C8 | D21: =D6+D7+D8 | E21: =E6+E7+E8 | F21: =F6+F7+F8 | G21: =G6+G7+G8 | H21: =H6+H7+H8 | I21: =I6+I7+I8 | ... Y21: =Y6+Y7+Y8
